ai_gemini_scraper/__Init__.py
ai_gemini_scraper/scraper.py
ai_gemini_scraper-0.1.3.dist-info/LICENSE
ai_gemini_scraper-0.1.3.dist-info/METADATA
ai_gemini_scraper-0.1.3.dist-info/WHEEL
ai_gemini_scraper-0.1.3.dist-info/top_level.txt
ai_gemini_scraper-0.1.3.dist-info/RECORD
