Metadata-Version: 2.2
Name: ai-gemini-scraper
Version: 0.1.3
Summary: A simple package for scraping websites and generating responses using Google's Generative AI.
Home-page: https://github.com/cyruszevirus/ai-scraper
Author: Cyrille Gattiker
Author-email: cyrille.gattiker@gmail.com
Classifier: Programming Language :: Python :: 3
Classifier: License :: OSI Approved :: MIT License
Classifier: Operating System :: OS Independent
Requires-Python: >=3.6
License-File: LICENSE
Requires-Dist: selenium
Requires-Dist: google-generativeai
Requires-Dist: urllib3
Dynamic: author
Dynamic: author-email
Dynamic: classifier
Dynamic: description
Dynamic: description-content-type
Dynamic: home-page
Dynamic: requires-dist
Dynamic: requires-python
Dynamic: summary
